ICICONSOLEGPT/BasicCypherCommands.py
ICICONSOLEGPT/Utilities.py
ICICONSOLEGPT/__init__.py
ICICONSOLEGPT/__main__.py
ICICONSOLEGPT/helpCypher.json
ICICONSOLEGPT-0.0.6.dist-info/LICENSE
ICICONSOLEGPT-0.0.6.dist-info/METADATA
ICICONSOLEGPT-0.0.6.dist-info/WHEEL
ICICONSOLEGPT-0.0.6.dist-info/entry_points.txt
ICICONSOLEGPT-0.0.6.dist-info/top_level.txt
ICICONSOLEGPT-0.0.6.dist-info/RECORD
