Metadata-Version: 2.1
Name: ICICONSOLEGPT
Version: 0.0.6
Summary: GPT Powered Command-line Interface tailored to working with Neo4j Knowledge Graph Databses hosted via Tapis Pods.
Author-email: Sahil Samar <sahilsamar031@gmail.com>
License: MIT License
Project-URL: Homepage, https://github.com/AD1616/ICICONSOLE/tree/main/ICICONSOLE_GPT
Keywords: Tapis,CLI,Agave,HPC,Tapis Pods,TACC,Neo4j
Classifier: License :: OSI Approved :: GNU General Public License (GPL)
Classifier: Programming Language :: Python
Classifier: Programming Language :: Python :: 3
Requires-Python: >=3.10
License-File: LICENSE
Requires-Dist: tapipy
Requires-Dist: py2neo
Requires-Dist: pandas
Requires-Dist: datascroller
Requires-Dist: openai
Provides-Extra: dev
